dtx_prompt_guard_client/__init__.py
dtx_prompt_guard_client/dlp.py
dtx_prompt_guard_client/guard.py
dtx_prompt_guard_client/guardv2.py
dtx_prompt_guard_client-0.3.0.dist-info/METADATA
dtx_prompt_guard_client-0.3.0.dist-info/WHEEL
dtx_prompt_guard_client-0.3.0.dist-info/RECORD
