Metadata-Version: 2.3
Name: dtx-prompt-guard-client
Version: 0.3.0
Summary: Detoxio AI Guardrails and Security APIs Client 
Author: Detoxio AI
Author-email: hello@detoxio.ai
Requires-Python: >=3.11,<4.0
Classifier: Programming Language :: Python :: 3
Classifier: Programming Language :: Python :: 3.11
Classifier: Programming Language :: Python :: 3.12
Classifier: Programming Language :: Python :: 3.13
Requires-Dist: pydantic (>=2.10.6,<3.0.0)
Requires-Dist: requests (>=2.32.3,<3.0.0)
